unWISExLens_lklh/ThreeXTwoACT.py
unWISExLens_lklh/ThreeXTwoACT.yaml
unWISExLens_lklh/ThreeXTwoACTPlanck.py
unWISExLens_lklh/ThreeXTwoACTPlanck.yaml
unWISExLens_lklh/ThreeXTwoPlanck.py
unWISExLens_lklh/ThreeXTwoPlanck.yaml
unWISExLens_lklh/XCorrACT.py
unWISExLens_lklh/XCorrACT.yaml
unWISExLens_lklh/XCorrACTPlanck.py
unWISExLens_lklh/XCorrACTPlanck.yaml
unWISExLens_lklh/XCorrPlanck.py
unWISExLens_lklh/XCorrPlanck.yaml
unWISExLens_lklh/__init__.py
unWISExLens_lklh/lensing_lklh_correction.py
unWISExLens_lklh/unWISExLensLklh.py
unWISExLens_lklh/unWISExLensLklh.yaml
unWISExLens_lklh/unWISExLensTheory.py
unWISExLens_lklh/auxiliary/__init__.py
unWISExLens_lklh/auxiliary/auxiliary_functions.py
unWISExLens_lklh/auxiliary/bias_coevolution.py
unWISExLens_lklh/auxiliary/binning_helpers.py
unWISExLens_lklh/auxiliary/dN_dz_aux.py
unWISExLens_lklh/auxiliary/pk_interpolator.py
unWISExLens_lklh/config_files/binning_setup.yaml
unWISExLens_lklh/config_files/covmat_filenames_baseline.yaml
unWISExLens_lklh/config_files/covmat_filenames_cmbmarg.yaml
unWISExLens_lklh/config_files/data_filenames.yaml
unWISExLens_lklh/param_prior_files/galaxy_dndz_pca_params_unWISExACT-DR6_blue.yaml
unWISExLens_lklh/param_prior_files/galaxy_dndz_pca_params_unWISExACT-DR6_green.yaml
unWISExLens_lklh/param_prior_files/galaxy_dndz_pca_params_unWISExPlanck-PR4_blue.yaml
unWISExLens_lklh/param_prior_files/galaxy_dndz_pca_params_unWISExPlanck-PR4_green.yaml
unWISExLens_lklh/param_prior_files/galaxy_nuisance_params_unWISExACT-DR6_blue.yaml
unWISExLens_lklh/param_prior_files/galaxy_nuisance_params_unWISExACT-DR6_green.yaml
unWISExLens_lklh/param_prior_files/galaxy_nuisance_params_unWISExPlanck-PR4_blue.yaml
unWISExLens_lklh/param_prior_files/galaxy_nuisance_params_unWISExPlanck-PR4_green.yaml
unWISExLens_lklh/theory_modules/__init__.py
unWISExLens_lklh/theory_modules/cross_dNdz_cosmo_correction.py
unWISExLens_lklh/theory_modules/model_helpers_unWISExLens.py
unWISExLens_lklh/theory_modules/unWISExkappa_model.py
unwisexlens_lklh-1.0.2.dist-info/licenses/LICENSE
unwisexlens_lklh-1.0.2.dist-info/WHEEL
unwisexlens_lklh-1.0.2.dist-info/METADATA
unwisexlens_lklh-1.0.2.dist-info/RECORD
