Metadata-Version: 2.4
Name: unWISExLens_lklh
Version: 1.0.2
Summary: likelihood for cross-correlation analysis using unWISE galaxies and CMB lensing reconstructions from ACT and Planck
Author-email: "Gerrit S. Farren" <gfarren@lbl.gov>
Classifier: License :: OSI Approved :: BSD License
License-File: LICENSE
Requires-Dist: numpy >=1
Requires-Dist: scipy >=1
Requires-Dist: cobaya >=3.5
Requires-Dist: healpy
Requires-Dist: camb >=1.5
Project-URL: Source, https://github.com/ACTCollaboration/unWISExLens_lklh
